akeuroo_deck/__init__.py
akeuroo_deck-2.0.1.dist-info/LICENSE.txt
akeuroo_deck-2.0.1.dist-info/METADATA
akeuroo_deck-2.0.1.dist-info/WHEEL
akeuroo_deck-2.0.1.dist-info/top_level.txt
akeuroo_deck-2.0.1.dist-info/RECORD
